flask_digest_auth/__init__.py
flask_digest_auth/algo.py
flask_digest_auth/auth.py
flask_digest_auth/test.py
flask_digest_auth-0.3.1.dist-info/LICENSE
flask_digest_auth-0.3.1.dist-info/METADATA
flask_digest_auth-0.3.1.dist-info/WHEEL
flask_digest_auth-0.3.1.dist-info/top_level.txt
flask_digest_auth-0.3.1.dist-info/RECORD
