Metadata-Version: 2.1
Name: flask-digest-auth
Version: 0.3.1
Summary: The Flask HTTP Digest Authentication project.
Home-page: https://github.com/imacat/flask-digest-auth
Author: imacat
Author-email: imacat@mail.imacat.idv.tw
Project-URL: Bug Tracker, https://github.com/imacat/flask-digest-auth/issues
Classifier: Programming Language :: Python :: 3
Classifier: License :: OSI Approved :: Apache Software License
Classifier: Operating System :: OS Independent
Classifier: Framework :: Flask
Classifier: Topic :: System :: Systems Administration :: Authentication/Directory
Classifier: Intended Audience :: Developers
Requires-Python: >=3.7
License-File: LICENSE
Requires-Dist: flask
Provides-Extra: flask_login
Requires-Dist: flask-login ; extra == 'flask_login'
